packageamit/__init__.py
packageamit-0.1.dist-info/METADATA
packageamit-0.1.dist-info/WHEEL
packageamit-0.1.dist-info/top_level.txt
packageamit-0.1.dist-info/RECORD
