Metadata-Version: 2.1
Name: packageamit
Version: 0.1
Summary: This is code with amit package
Home-page: UNKNOWN
Author: Harry
Author-email: UNKNOWN
License: UNKNOWN
Platform: UNKNOWN
